[
{
  "pk": 1, 
  "model": "auth.permission", 
  "fields": {
    "codename": "add_permission", 
    "name": "Can add permission", 
    "content_type": 1
  }
},
{
  "pk": 2, 
  "model": "auth.permission", 
  "fields": {
    "codename": "change_permission", 
    "name": "Can change permission", 
    "content_type": 1
  }
},
{
  "pk": 3, 
  "model": "auth.permission", 
  "fields": {
    "codename": "delete_permission", 
    "name": "Can delete permission", 
    "content_type": 1
  }
},
{
  "pk": 4, 
  "model": "auth.permission", 
  "fields": {
    "codename": "add_group", 
    "name": "Can add group", 
    "content_type": 2
  }
},
{
  "pk": 5, 
  "model": "auth.permission", 
  "fields": {
    "codename": "change_group", 
    "name": "Can change group", 
    "content_type": 2
  }
},
{
  "pk": 6, 
  "model": "auth.permission", 
  "fields": {
    "codename": "delete_group", 
    "name": "Can delete group", 
    "content_type": 2
  }
},
{
  "pk": 7, 
  "model": "auth.permission", 
  "fields": {
    "codename": "add_user", 
    "name": "Can add user", 
    "content_type": 3
  }
},
{
  "pk": 8, 
  "model": "auth.permission", 
  "fields": {
    "codename": "change_user", 
    "name": "Can change user", 
    "content_type": 3
  }
},
{
  "pk": 9, 
  "model": "auth.permission", 
  "fields": {
    "codename": "delete_user", 
    "name": "Can delete user", 
    "content_type": 3
  }
},
{
  "pk": 10, 
  "model": "auth.permission", 
  "fields": {
    "codename": "add_contenttype", 
    "name": "Can add content type", 
    "content_type": 4
  }
},
{
  "pk": 11, 
  "model": "auth.permission", 
  "fields": {
    "codename": "change_contenttype", 
    "name": "Can change content type", 
    "content_type": 4
  }
},
{
  "pk": 12, 
  "model": "auth.permission", 
  "fields": {
    "codename": "delete_contenttype", 
    "name": "Can delete content type", 
    "content_type": 4
  }
},
{
  "pk": 13, 
  "model": "auth.permission", 
  "fields": {
    "codename": "add_session", 
    "name": "Can add session", 
    "content_type": 5
  }
},
{
  "pk": 14, 
  "model": "auth.permission", 
  "fields": {
    "codename": "change_session", 
    "name": "Can change session", 
    "content_type": 5
  }
},
{
  "pk": 15, 
  "model": "auth.permission", 
  "fields": {
    "codename": "delete_session", 
    "name": "Can delete session", 
    "content_type": 5
  }
},
{
  "pk": 16, 
  "model": "auth.permission", 
  "fields": {
    "codename": "add_site", 
    "name": "Can add site", 
    "content_type": 6
  }
},
{
  "pk": 17, 
  "model": "auth.permission", 
  "fields": {
    "codename": "change_site", 
    "name": "Can change site", 
    "content_type": 6
  }
},
{
  "pk": 18, 
  "model": "auth.permission", 
  "fields": {
    "codename": "delete_site", 
    "name": "Can delete site", 
    "content_type": 6
  }
},
{
  "pk": 19, 
  "model": "auth.permission", 
  "fields": {
    "codename": "add_domain", 
    "name": "Can add Domain", 
    "content_type": 7
  }
},
{
  "pk": 20, 
  "model": "auth.permission", 
  "fields": {
    "codename": "change_domain", 
    "name": "Can change Domain", 
    "content_type": 7
  }
},
{
  "pk": 21, 
  "model": "auth.permission", 
  "fields": {
    "codename": "delete_domain", 
    "name": "Can delete Domain", 
    "content_type": 7
  }
},
{
  "pk": 22, 
  "model": "auth.permission", 
  "fields": {
    "codename": "add_alias", 
    "name": "Can add alias", 
    "content_type": 8
  }
},
{
  "pk": 23, 
  "model": "auth.permission", 
  "fields": {
    "codename": "change_alias", 
    "name": "Can change alias", 
    "content_type": 8
  }
},
{
  "pk": 24, 
  "model": "auth.permission", 
  "fields": {
    "codename": "delete_alias", 
    "name": "Can delete alias", 
    "content_type": 8
  }
},
{
  "pk": 25, 
  "model": "auth.permission", 
  "fields": {
    "codename": "add_site", 
    "name": "Can add site", 
    "content_type": 9
  }
},
{
  "pk": 26, 
  "model": "auth.permission", 
  "fields": {
    "codename": "change_site", 
    "name": "Can change site", 
    "content_type": 9
  }
},
{
  "pk": 27, 
  "model": "auth.permission", 
  "fields": {
    "codename": "delete_site", 
    "name": "Can delete site", 
    "content_type": 9
  }
},
{
  "pk": 28, 
  "model": "auth.permission", 
  "fields": {
    "codename": "add_template", 
    "name": "Can add Template", 
    "content_type": 10
  }
},
{
  "pk": 29, 
  "model": "auth.permission", 
  "fields": {
    "codename": "change_template", 
    "name": "Can change Template", 
    "content_type": 10
  }
},
{
  "pk": 30, 
  "model": "auth.permission", 
  "fields": {
    "codename": "delete_template", 
    "name": "Can delete Template", 
    "content_type": 10
  }
},
{
  "pk": 31, 
  "model": "auth.permission", 
  "fields": {
    "codename": "add_targetting", 
    "name": "Can add targetting", 
    "content_type": 11
  }
},
{
  "pk": 32, 
  "model": "auth.permission", 
  "fields": {
    "codename": "change_targetting", 
    "name": "Can change targetting", 
    "content_type": 11
  }
},
{
  "pk": 33, 
  "model": "auth.permission", 
  "fields": {
    "codename": "delete_targetting", 
    "name": "Can delete targetting", 
    "content_type": 11
  }
},
{
  "pk": 34, 
  "model": "auth.permission", 
  "fields": {
    "codename": "add_circle", 
    "name": "Can add Circle", 
    "content_type": 12
  }
},
{
  "pk": 35, 
  "model": "auth.permission", 
  "fields": {
    "codename": "change_circle", 
    "name": "Can change Circle", 
    "content_type": 12
  }
},
{
  "pk": 36, 
  "model": "auth.permission", 
  "fields": {
    "codename": "delete_circle", 
    "name": "Can delete Circle", 
    "content_type": 12
  }
},
{
  "pk": 37, 
  "model": "auth.permission", 
  "fields": {
    "codename": "add_member", 
    "name": "Can add Member", 
    "content_type": 13
  }
},
{
  "pk": 38, 
  "model": "auth.permission", 
  "fields": {
    "codename": "change_member", 
    "name": "Can change Member", 
    "content_type": 13
  }
},
{
  "pk": 39, 
  "model": "auth.permission", 
  "fields": {
    "codename": "delete_member", 
    "name": "Can delete Member", 
    "content_type": 13
  }
},
{
  "pk": 40, 
  "model": "auth.permission", 
  "fields": {
    "codename": "add_membership", 
    "name": "Can add Membership", 
    "content_type": 14
  }
},
{
  "pk": 41, 
  "model": "auth.permission", 
  "fields": {
    "codename": "change_membership", 
    "name": "Can change Membership", 
    "content_type": 14
  }
},
{
  "pk": 42, 
  "model": "auth.permission", 
  "fields": {
    "codename": "delete_membership", 
    "name": "Can delete Membership", 
    "content_type": 14
  }
},
{
  "pk": 43, 
  "model": "auth.permission", 
  "fields": {
    "codename": "add_publish", 
    "name": "Can add Publish", 
    "content_type": 15
  }
},
{
  "pk": 44, 
  "model": "auth.permission", 
  "fields": {
    "codename": "change_publish", 
    "name": "Can change Publish", 
    "content_type": 15
  }
},
{
  "pk": 45, 
  "model": "auth.permission", 
  "fields": {
    "codename": "delete_publish", 
    "name": "Can delete Publish", 
    "content_type": 15
  }
},
{
  "pk": 46, 
  "model": "auth.permission", 
  "fields": {
    "codename": "add_journal", 
    "name": "Can add Journal", 
    "content_type": 16
  }
},
{
  "pk": 47, 
  "model": "auth.permission", 
  "fields": {
    "codename": "change_journal", 
    "name": "Can change Journal", 
    "content_type": 16
  }
},
{
  "pk": 48, 
  "model": "auth.permission", 
  "fields": {
    "codename": "delete_journal", 
    "name": "Can delete Journal", 
    "content_type": 16
  }
},
{
  "pk": 49, 
  "model": "auth.permission", 
  "fields": {
    "codename": "add_systemevent", 
    "name": "Can add systemevent", 
    "content_type": 17
  }
},
{
  "pk": 50, 
  "model": "auth.permission", 
  "fields": {
    "codename": "change_systemevent", 
    "name": "Can change systemevent", 
    "content_type": 17
  }
},
{
  "pk": 51, 
  "model": "auth.permission", 
  "fields": {
    "codename": "delete_systemevent", 
    "name": "Can delete systemevent", 
    "content_type": 17
  }
},
{
  "pk": 52, 
  "model": "auth.permission", 
  "fields": {
    "codename": "add_systemeventsproperty", 
    "name": "Can add systemeventsproperty", 
    "content_type": 18
  }
},
{
  "pk": 53, 
  "model": "auth.permission", 
  "fields": {
    "codename": "change_systemeventsproperty", 
    "name": "Can change systemeventsproperty", 
    "content_type": 18
  }
},
{
  "pk": 54, 
  "model": "auth.permission", 
  "fields": {
    "codename": "delete_systemeventsproperty", 
    "name": "Can delete systemeventsproperty", 
    "content_type": 18
  }
},
{
  "pk": 55, 
  "model": "auth.permission", 
  "fields": {
    "codename": "add_message", 
    "name": "Can add message", 
    "content_type": 19
  }
},
{
  "pk": 56, 
  "model": "auth.permission", 
  "fields": {
    "codename": "change_message", 
    "name": "Can change message", 
    "content_type": 19
  }
},
{
  "pk": 57, 
  "model": "auth.permission", 
  "fields": {
    "codename": "delete_message", 
    "name": "Can delete message", 
    "content_type": 19
  }
},
{
  "pk": 58, 
  "model": "auth.permission", 
  "fields": {
    "codename": "add_provision", 
    "name": "Can add Provision", 
    "content_type": 20
  }
},
{
  "pk": 59, 
  "model": "auth.permission", 
  "fields": {
    "codename": "change_provision", 
    "name": "Can change Provision", 
    "content_type": 20
  }
},
{
  "pk": 60, 
  "model": "auth.permission", 
  "fields": {
    "codename": "delete_provision", 
    "name": "Can delete Provision", 
    "content_type": 20
  }
},
{
  "pk": 61, 
  "model": "auth.permission", 
  "fields": {
    "codename": "add_publication", 
    "name": "Can add publication", 
    "content_type": 21
  }
},
{
  "pk": 62, 
  "model": "auth.permission", 
  "fields": {
    "codename": "change_publication", 
    "name": "Can change publication", 
    "content_type": 21
  }
},
{
  "pk": 63, 
  "model": "auth.permission", 
  "fields": {
    "codename": "delete_publication", 
    "name": "Can delete publication", 
    "content_type": 21
  }
},
{
  "pk": 64, 
  "model": "auth.permission", 
  "fields": {
    "codename": "add_logentry", 
    "name": "Can add log entry", 
    "content_type": 22
  }
},
{
  "pk": 65, 
  "model": "auth.permission", 
  "fields": {
    "codename": "change_logentry", 
    "name": "Can change log entry", 
    "content_type": 22
  }
},
{
  "pk": 66, 
  "model": "auth.permission", 
  "fields": {
    "codename": "delete_logentry", 
    "name": "Can delete log entry", 
    "content_type": 22
  }
},
{
  "pk": 1, 
  "model": "auth.user", 
  "fields": {
    "username": "admin", 
    "first_name": "", 
    "last_name": "", 
    "is_active": true, 
    "is_superuser": true, 
    "is_staff": true, 
    "last_login": "2014-02-03T01:47:37.651Z", 
    "groups": [], 
    "user_permissions": [], 
    "password": "pbkdf2_sha256$10000$lNfSriJphUea$Sss5/pgACp2BqSd4N3bZr5OwmRJyaIciBE9zMAfxqDU=", 
    "email": "admin@admin.admin", 
    "date_joined": "2014-02-03T01:37:50.947Z"
  }
}
]
